bit/__init__.py
bit/bit.py
bitdotio/__init__.py
bitdotio/_bitdotio.py
bitdotio/_version.py
bitdotio/api_client.py
bitdotio/utils.py
bitdotio-2.2.1.dist-info/LICENSE
bitdotio-2.2.1.dist-info/METADATA
bitdotio-2.2.1.dist-info/WHEEL
bitdotio-2.2.1.dist-info/entry_points.txt
bitdotio-2.2.1.dist-info/top_level.txt
bitdotio-2.2.1.dist-info/RECORD
