Metadata-Version: 2.1
Name: bitdotio
Version: 2.2.1
Summary: bit.io Python SDK and CLI
Home-page: https://github.com/bitdotioinc/python-bitdotio
Author: bit.io
Author-email: python@bit.io
License: UNKNOWN
Project-URL: Bug Tracker, https://github.com/bitdotioinc/python-bitdotio/issues
Keywords: bit.io,Database,bit.io Python SDK
Platform: UNKNOWN
Classifier: Programming Language :: Python :: 3
Classifier: Operating System :: OS Independent
Requires-Python: >=3.7
License-File: LICENSE
Requires-Dist: requests (>=2.28.1)
Requires-Dist: click (>=8.0.1)
Provides-Extra: psycopg2
Requires-Dist: psycopg2 (>=2.8.6) ; extra == 'psycopg2'
Provides-Extra: psycopg2-binary
Requires-Dist: psycopg2-binary (>=2.8.6) ; extra == 'psycopg2-binary'
